niels_coloredlogger/__init__.py
niels_coloredlogger/logger.py
niels_coloredlogger-0.2.dist-info/METADATA
niels_coloredlogger-0.2.dist-info/WHEEL
niels_coloredlogger-0.2.dist-info/top_level.txt
niels_coloredlogger-0.2.dist-info/RECORD
