Metadata-Version: 2.1
Name: niels_coloredlogger
Version: 0.2
Author: Niels
Requires-Dist: coloredlogs
Requires-Dist: logging
